foe/__init__.py
foe/evaluator.py
foe/logic.py
foe/prover.py
foe/parser/__init__.py
foe/parser/tptp.py
foe/parser/tptp_grammar.lark
foe-0.0.11.dist-info/LICENSE
foe-0.0.11.dist-info/METADATA
foe-0.0.11.dist-info/WHEEL
foe-0.0.11.dist-info/top_level.txt
foe-0.0.11.dist-info/RECORD
